{
  "last_updated": "2026-06-17T17:07:08Z",
  "stocks": [
    {
      "ticker": "AAPL",
      "name": "Apple Inc.",
      "description": "Consumer electronics, software and services. Maker of iPhone, Mac, iPad and the iOS ecosystem.",
      "color": "#555555",
      "price": 297.2,
      "prev_close": 298.9,
      "change_pct": -0.57,
      "trailing_pe": 36.0,
      "eps": 8.26,
      "market_cap": 4365080592384
    },
    {
      "ticker": "MSFT",
      "name": "Microsoft Corporation",
      "description": "Enterprise software, cloud computing (Azure), and productivity tools including Office 365 and Teams.",
      "color": "#0078d4",
      "price": 383.87,
      "prev_close": 393.15,
      "change_pct": -2.36,
      "trailing_pe": 22.9,
      "eps": 16.78,
      "market_cap": 2851627597824
    },
    {
      "ticker": "GOOGL",
      "name": "Alphabet Inc.",
      "description": "Parent of Google. Dominates search, digital ads, YouTube and is a major cloud provider.",
      "color": "#4285f4",
      "price": 364.77,
      "prev_close": 371.97,
      "change_pct": -1.94,
      "trailing_pe": 27.8,
      "eps": 13.1,
      "market_cap": 4450888450048
    },
    {
      "ticker": "AMZN",
      "name": "Amazon.com, Inc.",
      "description": "E-commerce and cloud infrastructure leader (AWS). Also expanding in advertising and AI services.",
      "color": "#ff9900",
      "price": 239.53,
      "prev_close": 245.77,
      "change_pct": -2.54,
      "trailing_pe": 30.8,
      "eps": 7.77,
      "market_cap": 2576650600448
    },
    {
      "ticker": "NVDA",
      "name": "NVIDIA Corporation",
      "description": "Designs GPUs and AI accelerators. The dominant supplier of chips powering AI training and inference.",
      "color": "#76b900",
      "price": 207.05,
      "prev_close": 207.55,
      "change_pct": -0.24,
      "trailing_pe": 31.7,
      "eps": 6.53,
      "market_cap": 5015078961152
    },
    {
      "ticker": "META",
      "name": "Meta Platforms, Inc.",
      "description": "Social media conglomerate. Operates Facebook, Instagram, WhatsApp and invests heavily in VR/AR.",
      "color": "#0668e1",
      "price": 577.87,
      "prev_close": 597.68,
      "change_pct": -3.32,
      "trailing_pe": 21.0,
      "eps": 27.49,
      "market_cap": 1466878656512
    },
    {
      "ticker": "TSLA",
      "name": "Tesla, Inc.",
      "description": "Electric vehicles, energy storage and solar. Also developing autonomous driving and robotics (Optimus).",
      "color": "#cc0000",
      "price": 403.97,
      "prev_close": 402.84,
      "change_pct": 0.28,
      "trailing_pe": 370.6,
      "eps": 1.09,
      "market_cap": 1517162201088
    }
  ],
  "pe_history": {
    "AAPL": {
      "dates": [
        "Jul 21",
        "Aug 21",
        "Sep 21",
        "Oct 21",
        "Nov 21",
        "Dec 21",
        "Jan 22",
        "Feb 22",
        "Mar 22",
        "Apr 22",
        "May 22",
        "Jun 22",
        "Jul 22",
        "Aug 22",
        "Sep 22",
        "Oct 22",
        "Nov 22",
        "Dec 22",
        "Jan 23",
        "Feb 23",
        "Mar 23",
        "Apr 23",
        "May 23",
        "Jun 23",
        "Jul 23",
        "Aug 23",
        "Sep 23",
        "Oct 23",
        "Nov 23",
        "Dec 23",
        "Jan 24",
        "Feb 24",
        "Mar 24",
        "Apr 24",
        "May 24",
        "Jun 24",
        "Jul 24",
        "Aug 24",
        "Sep 24",
        "Oct 24",
        "Nov 24",
        "Dec 24",
        "Jan 25",
        "Feb 25",
        "Mar 25",
        "Apr 25",
        "May 25",
        "Jun 25",
        "Jul 25",
        "Aug 25",
        "Sep 25",
        "Oct 25",
        "Nov 25",
        "Dec 25",
        "Jan 26",
        "Feb 26",
        "Mar 26",
        "Apr 26",
        "May 26",
        "Jun 26"
      ],
      "values": [
        17.2,
        17.9,
        16.7,
        17.7,
        19.5,
        21.0,
        20.7,
        19.5,
        20.7,
        18.7,
        17.6,
        16.2,
        19.3,
        18.7,
        16.4,
        18.2,
        17.6,
        15.5,
        17.2,
        17.5,
        19.7,
        20.2,
        21.1,
        23.2,
        23.5,
        22.4,
        20.5,
        20.4,
        22.7,
        23.0,
        22.1,
        21.6,
        20.6,
        20.4,
        23.0,
        25.3,
        26.7,
        27.5,
        28.0,
        27.1,
        28.5,
        30.1,
        28.4,
        29.1,
        26.8,
        25.6,
        24.2,
        24.7,
        25.0,
        28.0,
        30.7,
        32.6,
        33.7,
        32.9,
        31.4,
        31.9,
        30.7,
        32.8,
        37.7,
        36.0
      ],
      "color": "#555555"
    },
    "MSFT": {
      "dates": [
        "Jul 21",
        "Aug 21",
        "Sep 21",
        "Oct 21",
        "Nov 21",
        "Dec 21",
        "Jan 22",
        "Feb 22",
        "Mar 22",
        "Apr 22",
        "May 22",
        "Jun 22",
        "Jul 22",
        "Aug 22",
        "Sep 22",
        "Oct 22",
        "Nov 22",
        "Dec 22",
        "Jan 23",
        "Feb 23",
        "Mar 23",
        "Apr 23",
        "May 23",
        "Jun 23",
        "Jul 23",
        "Aug 23",
        "Sep 23",
        "Oct 23",
        "Nov 23",
        "Dec 23",
        "Jan 24",
        "Feb 24",
        "Mar 24",
        "Apr 24",
        "May 24",
        "Jun 24",
        "Jul 24",
        "Aug 24",
        "Sep 24",
        "Oct 24",
        "Nov 24",
        "Dec 24",
        "Jan 25",
        "Feb 25",
        "Mar 25",
        "Apr 25",
        "May 25",
        "Jun 25",
        "Jul 25",
        "Aug 25",
        "Sep 25",
        "Oct 25",
        "Nov 25",
        "Dec 25",
        "Jan 26",
        "Feb 26",
        "Mar 26",
        "Apr 26",
        "May 26",
        "Jun 26"
      ],
      "values": [
        16.3,
        17.3,
        16.2,
        19.0,
        18.9,
        19.3,
        17.9,
        17.2,
        17.7,
        16.0,
        15.6,
        14.8,
        16.2,
        15.1,
        13.5,
        13.4,
        14.7,
        13.9,
        14.4,
        14.5,
        16.7,
        17.8,
        19.1,
        19.8,
        19.6,
        19.1,
        18.4,
        19.7,
        22.1,
        22.0,
        23.2,
        24.2,
        24.6,
        22.8,
        24.3,
        26.2,
        24.5,
        24.5,
        25.3,
        23.9,
        24.9,
        24.8,
        24.4,
        23.4,
        22.2,
        23.3,
        27.2,
        29.4,
        31.5,
        30.0,
        30.7,
        30.7,
        29.1,
        28.7,
        25.5,
        23.3,
        22.0,
        24.2,
        26.8,
        22.9
      ],
      "color": "#0078d4"
    },
    "GOOGL": {
      "dates": [
        "Jul 21",
        "Aug 21",
        "Sep 21",
        "Oct 21",
        "Nov 21",
        "Dec 21",
        "Jan 22",
        "Feb 22",
        "Mar 22",
        "Apr 22",
        "May 22",
        "Jun 22",
        "Jul 22",
        "Aug 22",
        "Sep 22",
        "Oct 22",
        "Nov 22",
        "Dec 22",
        "Jan 23",
        "Feb 23",
        "Mar 23",
        "Apr 23",
        "May 23",
        "Jun 23",
        "Jul 23",
        "Aug 23",
        "Sep 23",
        "Oct 23",
        "Nov 23",
        "Dec 23",
        "Jan 24",
        "Feb 24",
        "Mar 24",
        "Apr 24",
        "May 24",
        "Jun 24",
        "Jul 24",
        "Aug 24",
        "Sep 24",
        "Oct 24",
        "Nov 24",
        "Dec 24",
        "Jan 25",
        "Feb 25",
        "Mar 25",
        "Apr 25",
        "May 25",
        "Jun 25",
        "Jul 25",
        "Aug 25",
        "Sep 25",
        "Oct 25",
        "Nov 25",
        "Dec 25",
        "Jan 26",
        "Feb 26",
        "Mar 26",
        "Apr 26",
        "May 26",
        "Jun 26"
      ],
      "values": [
        10.2,
        10.9,
        10.1,
        11.2,
        10.7,
        11.0,
        10.2,
        10.2,
        10.5,
        8.6,
        8.6,
        8.2,
        8.8,
        8.2,
        7.2,
        7.2,
        7.6,
        6.7,
        7.5,
        6.8,
        7.8,
        8.1,
        9.3,
        9.1,
        10.0,
        10.3,
        9.9,
        9.4,
        10.0,
        10.6,
        10.6,
        10.5,
        11.4,
        12.3,
        13.1,
        13.8,
        13.0,
        12.4,
        12.6,
        13.0,
        12.8,
        14.4,
        15.5,
        12.9,
        11.7,
        12.1,
        13.1,
        13.4,
        14.6,
        16.2,
        18.5,
        21.4,
        24.4,
        23.8,
        25.8,
        23.8,
        21.9,
        29.4,
        29.0,
        27.8
      ],
      "color": "#4285f4"
    },
    "AMZN": {
      "dates": [
        "Jul 21",
        "Aug 21",
        "Sep 21",
        "Oct 21",
        "Nov 21",
        "Dec 21",
        "Jan 22",
        "Feb 22",
        "Mar 22",
        "Apr 22",
        "May 22",
        "Jun 22",
        "Jul 22",
        "Aug 22",
        "Sep 22",
        "Oct 22",
        "Nov 22",
        "Dec 22",
        "Jan 23",
        "Feb 23",
        "Mar 23",
        "Apr 23",
        "May 23",
        "Jun 23",
        "Jul 23",
        "Aug 23",
        "Sep 23",
        "Oct 23",
        "Nov 23",
        "Dec 23",
        "Jan 24",
        "Feb 24",
        "Mar 24",
        "Apr 24",
        "May 24",
        "Jun 24",
        "Jul 24",
        "Aug 24",
        "Sep 24",
        "Oct 24",
        "Nov 24",
        "Dec 24",
        "Jan 25",
        "Feb 25",
        "Mar 25",
        "Apr 25",
        "May 25",
        "Jun 25",
        "Jul 25",
        "Aug 25",
        "Sep 25",
        "Oct 25",
        "Nov 25",
        "Dec 25",
        "Jan 26",
        "Feb 26",
        "Mar 26",
        "Apr 26",
        "May 26",
        "Jun 26"
      ],
      "values": [
        21.4,
        22.3,
        21.1,
        21.7,
        22.6,
        21.5,
        19.3,
        19.8,
        21.0,
        16.0,
        15.5,
        13.7,
        17.4,
        16.3,
        14.5,
        13.2,
        12.4,
        10.8,
        13.3,
        12.1,
        13.3,
        13.6,
        15.5,
        16.8,
        17.2,
        17.8,
        16.4,
        17.1,
        18.8,
        19.6,
        20.0,
        22.7,
        23.2,
        22.5,
        22.7,
        24.9,
        24.1,
        23.0,
        24.0,
        24.0,
        26.8,
        28.2,
        30.6,
        27.3,
        24.5,
        23.7,
        26.4,
        28.2,
        30.1,
        29.5,
        28.3,
        31.4,
        30.0,
        29.7,
        30.8,
        27.0,
        26.8,
        34.1,
        34.8,
        30.8
      ],
      "color": "#ff9900"
    },
    "NVDA": {
      "dates": [
        "Jul 21",
        "Aug 21",
        "Sep 21",
        "Oct 21",
        "Nov 21",
        "Dec 21",
        "Jan 22",
        "Feb 22",
        "Mar 22",
        "Apr 22",
        "May 22",
        "Jun 22",
        "Jul 22",
        "Aug 22",
        "Sep 22",
        "Oct 22",
        "Nov 22",
        "Dec 22",
        "Jan 23",
        "Feb 23",
        "Mar 23",
        "Apr 23",
        "May 23",
        "Jun 23",
        "Jul 23",
        "Aug 23",
        "Sep 23",
        "Oct 23",
        "Nov 23",
        "Dec 23",
        "Jan 24",
        "Feb 24",
        "Mar 24",
        "Apr 24",
        "May 24",
        "Jun 24",
        "Jul 24",
        "Aug 24",
        "Sep 24",
        "Oct 24",
        "Nov 24",
        "Dec 24",
        "Jan 25",
        "Feb 25",
        "Mar 25",
        "Apr 25",
        "May 25",
        "Jun 25",
        "Jul 25",
        "Aug 25",
        "Sep 25",
        "Oct 25",
        "Nov 25",
        "Dec 25",
        "Jan 26",
        "Feb 26",
        "Mar 26",
        "Apr 26",
        "May 26",
        "Jun 26"
      ],
      "values": [
        3.0,
        3.4,
        3.2,
        3.9,
        5.0,
        4.5,
        3.7,
        3.7,
        4.2,
        2.8,
        2.9,
        2.3,
        2.8,
        2.3,
        1.9,
        2.1,
        2.6,
        2.2,
        3.0,
        3.5,
        4.2,
        4.2,
        5.8,
        6.5,
        7.1,
        7.5,
        6.6,
        6.2,
        7.1,
        7.6,
        9.4,
        12.1,
        13.8,
        13.2,
        16.8,
        18.9,
        17.9,
        18.3,
        18.6,
        20.3,
        21.1,
        20.5,
        18.4,
        19.1,
        16.6,
        16.7,
        20.7,
        24.2,
        27.2,
        26.6,
        28.5,
        31.0,
        27.1,
        28.5,
        29.2,
        27.1,
        26.7,
        30.5,
        32.3,
        31.7
      ],
      "color": "#76b900"
    },
    "META": {
      "dates": [
        "Jul 21",
        "Aug 21",
        "Sep 21",
        "Oct 21",
        "Nov 21",
        "Dec 21",
        "Jan 22",
        "Feb 22",
        "Mar 22",
        "Apr 22",
        "May 22",
        "Jun 22",
        "Jul 22",
        "Aug 22",
        "Sep 22",
        "Oct 22",
        "Nov 22",
        "Dec 22",
        "Jan 23",
        "Feb 23",
        "Mar 23",
        "Apr 23",
        "May 23",
        "Jun 23",
        "Jul 23",
        "Aug 23",
        "Sep 23",
        "Oct 23",
        "Nov 23",
        "Dec 23",
        "Jan 24",
        "Feb 24",
        "Mar 24",
        "Apr 24",
        "May 24",
        "Jun 24",
        "Jul 24",
        "Aug 24",
        "Sep 24",
        "Oct 24",
        "Nov 24",
        "Dec 24",
        "Jan 25",
        "Feb 25",
        "Mar 25",
        "Apr 25",
        "May 25",
        "Jun 25",
        "Jul 25",
        "Aug 25",
        "Sep 25",
        "Oct 25",
        "Nov 25",
        "Dec 25",
        "Jan 26",
        "Feb 26",
        "Mar 26",
        "Apr 26",
        "May 26",
        "Jun 26"
      ],
      "values": [
        12.8,
        13.7,
        12.2,
        11.7,
        11.7,
        12.1,
        11.3,
        7.6,
        8.0,
        7.2,
        7.0,
        5.8,
        5.7,
        5.9,
        4.9,
        3.4,
        4.3,
        4.3,
        5.4,
        6.3,
        7.6,
        8.7,
        9.5,
        10.3,
        11.5,
        10.7,
        10.8,
        10.9,
        11.8,
        12.8,
        14.1,
        17.7,
        17.5,
        15.5,
        16.9,
        18.2,
        17.2,
        18.8,
        20.7,
        20.5,
        20.8,
        21.2,
        24.9,
        24.2,
        20.9,
        19.9,
        23.5,
        26.7,
        28.0,
        26.8,
        26.6,
        23.5,
        23.5,
        23.9,
        26.0,
        23.5,
        20.8,
        22.2,
        23.0,
        21.0
      ],
      "color": "#0668e1"
    },
    "TSLA": {
      "dates": [
        "Jul 21",
        "Aug 21",
        "Sep 21",
        "Oct 21",
        "Nov 21",
        "Dec 21",
        "Jan 22",
        "Feb 22",
        "Mar 22",
        "Apr 22",
        "May 22",
        "Jun 22",
        "Jul 22",
        "Aug 22",
        "Sep 22",
        "Oct 22",
        "Nov 22",
        "Dec 22",
        "Jan 23",
        "Feb 23",
        "Mar 23",
        "Apr 23",
        "May 23",
        "Jun 23",
        "Jul 23",
        "Aug 23",
        "Sep 23",
        "Oct 23",
        "Nov 23",
        "Dec 23",
        "Jan 24",
        "Feb 24",
        "Mar 24",
        "Apr 24",
        "May 24",
        "Jun 24",
        "Jul 24",
        "Aug 24",
        "Sep 24",
        "Oct 24",
        "Nov 24",
        "Dec 24",
        "Jan 25",
        "Feb 25",
        "Mar 25",
        "Apr 25",
        "May 25",
        "Jun 25",
        "Jul 25",
        "Aug 25",
        "Sep 25",
        "Oct 25",
        "Nov 25",
        "Dec 25",
        "Jan 26",
        "Feb 26",
        "Mar 26",
        "Apr 26",
        "May 26",
        "Jun 26"
      ],
      "values": [
        210.2,
        225.0,
        237.1,
        340.7,
        350.1,
        323.2,
        286.5,
        266.2,
        329.5,
        266.3,
        231.9,
        205.9,
        272.6,
        252.9,
        243.3,
        208.8,
        178.6,
        113.0,
        158.9,
        188.7,
        190.3,
        150.7,
        187.1,
        240.2,
        245.3,
        236.8,
        229.6,
        184.3,
        220.3,
        228.0,
        171.8,
        185.2,
        161.3,
        168.1,
        163.4,
        181.5,
        212.9,
        196.4,
        240.0,
        229.2,
        316.7,
        370.5,
        371.2,
        268.8,
        237.8,
        258.9,
        317.9,
        291.4,
        282.8,
        306.3,
        408.0,
        418.9,
        394.7,
        412.6,
        394.9,
        369.3,
        341.1,
        350.1,
        399.8,
        370.6
      ],
      "color": "#cc0000"
    }
  }
}